AUTHORS
LICENSE
MANIFEST.in
README.rst
setup.py
nodeshot/.DS_Store
nodeshot/._.DS_Store
nodeshot/__init__.py
nodeshot/dashboard.py
nodeshot.egg-info/PKG-INFO
nodeshot.egg-info/SOURCES.txt
nodeshot.egg-info/dependency_links.txt
nodeshot.egg-info/not-zip-safe
nodeshot.egg-info/requires.txt
nodeshot.egg-info/top_level.txt
nodeshot/bin/nodeshot
nodeshot/community/.DS_Store
nodeshot/community/._.DS_Store
nodeshot/community/__init__.py
nodeshot/community/mailing/.DS_Store
nodeshot/community/mailing/._.DS_Store
nodeshot/community/mailing/__init__.py
nodeshot/community/mailing/admin.py
nodeshot/community/mailing/serializers.py
nodeshot/community/mailing/settings.py
nodeshot/community/mailing/tests.py
nodeshot/community/mailing/urls.py
nodeshot/community/mailing/views.py
nodeshot/community/mailing/models/__init__.py
nodeshot/community/mailing/models/choices.py
nodeshot/community/mailing/models/inward.py
nodeshot/community/mailing/models/outward.py
nodeshot/community/mailing/templates/.DS_Store
nodeshot/community/mailing/templates/._.DS_Store
nodeshot/community/mailing/templates/admin/outward_change_form.html
nodeshot/community/notifications/__init__.py
nodeshot/community/notifications/admin.py
nodeshot/community/notifications/serializers.py
nodeshot/community/notifications/settings.py
nodeshot/community/notifications/tasks.py
nodeshot/community/notifications/tests.py
nodeshot/community/notifications/urls.py
nodeshot/community/notifications/views.py
nodeshot/community/notifications/management/__init__.py
nodeshot/community/notifications/management/commands/__init__.py
nodeshot/community/notifications/management/commands/purge_notifications.py
nodeshot/community/notifications/models/__init__.py
nodeshot/community/notifications/models/notification.py
nodeshot/community/notifications/models/user_settings.py
nodeshot/community/notifications/registrars/__init__.py
nodeshot/community/notifications/registrars/nodes.py
nodeshot/community/participation/__init__.py
nodeshot/community/participation/admin.py
nodeshot/community/participation/serializers.py
nodeshot/community/participation/tasks.py
nodeshot/community/participation/tests.py
