Metadata-Version: 1.1
Name: nodeshot
Version: 1.0.pre-alpha
Summary: Extensible Django web application for management of community-led georeferenced data.
Home-page: https://github.com/ninuxorg/nodeshot
Author: Federico Capoano
Author-email: nodeshot@ml.ninux.org
License: GPL3
Download-URL: https://github.com/ninuxorg/nodeshot/releases
Platform: UNKNOWN
Classifier: Development Status :: 3 - Alpha
Classifier: Environment :: Web Environment
Classifier: Intended Audience :: Developers
Classifier: License :: OSI Approved :: GNU General Public License v3 (GPLv3)
Classifier: Operating System :: POSIX
Classifier: Programming Language :: Python
Classifier: Topic :: Internet :: WWW/HTTP
Classifier: Framework :: Django
